<?xml version="1.0"?>
<dbc>
<name>LoadingScreenTaxiSplines</name>

<field>
    <name>id</name>
    <type>int32</type>
<key>
    <type>primary</type>
</key>
</field>

<field>
    <name>path_id</name>
    <type>int32</type>
<key>
    <type>foreign</type>
    <parent>TaxiPath</parent>
</key>
</field>

<field>
    <name>locx</name>
    <type>float[8]</type>
</field>

<field>
    <name>locy</name>
    <type>float[8]</type>
</field>

<field>
    <name>leg_index</name>
    <type>int32</type>
</field>

</dbc>
